AUTHORS.txt
CHANGES.rst
LICENSE.txt
MANIFEST.in
README.rst
setup.py
django_ichypd.egg-info/PKG-INFO
django_ichypd.egg-info/SOURCES.txt
django_ichypd.egg-info/dependency_links.txt
django_ichypd.egg-info/requires.txt
django_ichypd.egg-info/top_level.txt
ichypd/__init__.py
ichypd/admin.py
ichypd/models.py
ichypd/views.py
ichypd/templates/ichypd/admin/csv_export_change_list.html